browser_hz/__init__.py
browser_hz/browser.py
browser_hz/browser_factory.py
browser_hz/browser_options.py
browser_hz/browsers.py
browser_hz/helpers/__init__.py
browser_hz/helpers/element_helper.py
browser_hz/helpers/network_helper.py
browser_hz/helpers/wait_helper.py
browser_hz-4.1.1.dist-info/METADATA
browser_hz-4.1.1.dist-info/WHEEL
browser_hz-4.1.1.dist-info/RECORD
