Metadata-Version: 2.1
Name: browser-hz
Version: 4.1.1
Summary: Tailored Selenium Wire extension for in-house project development.
Author: Hubert Zajac
Author-email: hubertzajac6@gmail.com
Requires-Python: >=3.11,<4.0
Classifier: Programming Language :: Python :: 3
Classifier: Programming Language :: Python :: 3.11
Classifier: Programming Language :: Python :: 3.12
Requires-Dist: mypy (>=1.5.1,<2.0.0)
Requires-Dist: pylint (>=2.17.5,<3.0.0)
Requires-Dist: pytest (>=7.3.1,<8.0.0)
Requires-Dist: selenium-wire (>=5.1.0,<6.0.0)
Requires-Dist: webdriver-manager (>=4.0.1,<5.0.0)
